state_machine_py/__init__.py
state_machine_py/abstract_state.py
state_machine_py/state_machine.py
example_pkg_muzudho-0.0.1.dist-info/LICENSE
example_pkg_muzudho-0.0.1.dist-info/METADATA
example_pkg_muzudho-0.0.1.dist-info/WHEEL
example_pkg_muzudho-0.0.1.dist-info/top_level.txt
example_pkg_muzudho-0.0.1.dist-info/RECORD
